cqasm/__init__.py
cqasm/v3x/values.py
cqasm/v3x/semantic.py
cqasm/v3x/primitives.py
cqasm/v3x/__init__.py
cqasm/v3x/types.py
cqasm/v3x/ast.py
cqasm/v3x/instruction.py
libqasm-1.2.1.dist-info/RECORD
libqasm-1.2.1.dist-info/WHEEL
libqasm-1.2.1.dist-info/top_level.txt
libqasm-1.2.1.dist-info/METADATA
libqasm-1.2.1.dist-info/licenses/LICENSE.md
libqasm/__init__.py
libqasm/_libqasm.cpython-39-darwin.so
libqasm/libqasm.py
